{
"d" : {
"__metadata" : {
"uri" : "http://dxbreach.os.eidos.com:443/api/GenericDtoResult(151511L)", "type" : "game.GenericDtoResult"
}, "i64_resultId" : 151511, "i32_code" : 0, "s_message" : "ok", "c_dto" : {
"__metadata" : {
"type" : "com.see.game.ghostnetworks.dtos.GhostNetworkDTO"
}, "s_id" : "5e4bd28a1006a90d49d32e78", "i32_layout" : 8, "dto_created" : "datetimeoffset'2020-02-18T12:03:21Z'", "dto_ghostNetworkDate" : "datetimeoffset'2020-03-09T00:00:00Z'", "i32_effectiveDaySinceEpoch" : 18330, "dto_expirationDate" : "datetimeoffset'2020-03-10T00:00:00Z'", "i32_difficultyTier" : 4, "c_nodes" : {
"__metadata" : {
"type" : "java.util.HashMap"
}, "c_0" : {
"__metadata" : {
"type" : "com.see.game.ghostnetworks.dtos.GhostNetworksNode"
}, "i32_mapSettingId" : 1000094, "i32_nodeId" : 0, "c_modifiers" : {
"__metadata" : {
"type" : "java.util.ArrayList"
}
}
}, "c_1" : {
"__metadata" : {
"type" : "com.see.game.ghostnetworks.dtos.GhostNetworksNode"
}, "i32_mapSettingId" : 1050096, "i32_nodeId" : 1, "c_modifiers" : {
"__metadata" : {
"type" : "java.util.ArrayList"
}, "i64_0" : 26
}
}, "c_2" : {
"__metadata" : {
"type" : "com.see.game.ghostnetworks.dtos.GhostNetworksNode"
}, "i32_mapSettingId" : 1050230, "i32_nodeId" : 2, "c_modifiers" : {
"__metadata" : {
"type" : "java.util.ArrayList"
}
}
}, "c_3" : {
"__metadata" : {
"type" : "com.see.game.ghostnetworks.dtos.GhostNetworksNode"
}, "i32_mapSettingId" : 1000098, "i32_nodeId" : 3, "c_modifiers" : {
"__metadata" : {
"type" : "java.util.ArrayList"
}, "i64_0" : 22
}
}, "c_4" : {
"__metadata" : {
"type" : "com.see.game.ghostnetworks.dtos.GhostNetworksNode"
}, "i32_mapSettingId" : 1050149, "i32_nodeId" : 4, "c_modifiers" : {
"__metadata" : {
"type" : "java.util.ArrayList"
}
}
}, "c_5" : {
"__metadata" : {
"type" : "com.see.game.ghostnetworks.dtos.GhostNetworksNode"
}, "i32_mapSettingId" : 1050160, "i32_nodeId" : 5, "c_modifiers" : {
"__metadata" : {
"type" : "java.util.ArrayList"
}, "i64_0" : 52
}
}, "c_6" : {
"__metadata" : {
"type" : "com.see.game.ghostnetworks.dtos.GhostNetworksNode"
}, "i32_mapSettingId" : 1050233, "i32_nodeId" : 6, "c_modifiers" : {
"__metadata" : {
"type" : "java.util.ArrayList"
}
}
}, "c_7" : {
"__metadata" : {
"type" : "com.see.game.ghostnetworks.dtos.GhostNetworksNode"
}, "i32_mapSettingId" : 1000097, "i32_nodeId" : 7, "c_modifiers" : {
"__metadata" : {
"type" : "java.util.ArrayList"
}, "i64_0" : 4
}
}, "c_8" : {
"__metadata" : {
"type" : "com.see.game.ghostnetworks.dtos.GhostNetworksNode"
}, "i32_mapSettingId" : 1000135, "i32_nodeId" : 8, "c_modifiers" : {
"__metadata" : {
"type" : "java.util.ArrayList"
}
}
}, "c_9" : {
"__metadata" : {
"type" : "com.see.game.ghostnetworks.dtos.GhostNetworksNode"
}, "i32_mapSettingId" : 1050173, "i32_nodeId" : 9, "c_modifiers" : {
"__metadata" : {
"type" : "java.util.ArrayList"
}, "i64_0" : 12
}
}
}, "c_normalRewardNodes" : {
"__metadata" : {
"type" : "java.util.ArrayList"
}, "i32_0" : 0, "i32_1" : 1, "i32_2" : 2, "i32_3" : 3, "i32_4" : 4
}, "c_worldRewardNodes" : {
"__metadata" : {
"type" : "java.util.ArrayList"
}, "i32_0" : 1000
}
}
}
}